{
  "name": "ANTI_AIR",
  "health": 100,
  "mp": 6,
  "ammo": 9,
  "fuel": 60,
  "turn_fuel": 0,
  "hidden_turn_fuel": 0,
  "vision": 2,
  "min_range": 1,
  "max_range": 1,
  "movement_type": 2,
  "cost": 8000,
  "can_supply": false,
  "can_capture": false,
  "can_move_and_attack": true,
  "can_hide": false,
  "can_dive": false,
  "weapons": [7, -1],
  "damage_table": {
    "Artillery Cannon": 75,
    "Bazooka": 65,
    "Light Tank Cannon": 85,
    "Machine Gun": 5,
    "Medium Tank Cannon": 105,
    "Rockets": 85,
    "Tank Machine Gun": 4,
    "Vulcan Cannon": 45
  },
  "can_carry": false,
  "carrying_types": [],
  "carrying_size": 0,
  "description": "ANTI_AIR_DESCRIPTION"
}
